just_fix_windows_console/__init__.py
just_fix_windows_console/py.typed
just_fix_windows_console_autofix.pth
just_fix_windows_console-0.2.2.dist-info/METADATA
just_fix_windows_console-0.2.2.dist-info/WHEEL
just_fix_windows_console-0.2.2.dist-info/licenses/LICENSE
just_fix_windows_console-0.2.2.dist-info/RECORD
