Metadata-Version: 2.4
Name: just-fix-windows-console
Version: 0.2.2
Summary: A tiny, dependency-free Python module that enables ANSI / VT escape sequence processing on Windows consoles.
Author-email: Dheepak Krishnamurthy <1813121+kdheepak@users.noreply.github.com>
License-File: LICENSE
Requires-Python: >=3.13
